{"about.md":"Cb4mPQTN","blogs_2026-02-16.md":"EXj60Pqi","blogs_2026-05-02.md":"B8WxOkOc","blogs_index.md":"Ce6hpifo","channels_dingtalk.md":"C1DySc0e","channels_discord.md":"Cb2nTyCY","channels_feishu.md":"B0hEUHzt","channels_index.md":"Bjs0ySp7","channels_matrix.md":"OoAKZKA6","channels_misskey.md":"CqTBAr4R","channels_qq.md":"C1XA2svi","channels_slack.md":"DTNaId6O","channels_telegram.md":"Y8XRMSnR","channels_wechatoa.md":"GeMTo4NJ","channels_wecom.md":"hWhBA2yU","channels_weixin.md":"Bn0v7UX1","getting-started_access.md":"HF9vlm7w","getting-started_bot.md":"CULv0VL-","getting-started_channels.md":"BOsIHBIy","getting-started_compaction.md":"DiGphYxi","getting-started_container.md":"BUf_Z2Ay","getting-started_email.md":"ClGYtEJO","getting-started_files.md":"D3jiVPFO","getting-started_heartbeat.md":"HlEetMRI","getting-started_mcp.md":"DVpavUVC","getting-started_memory.md":"DiDftUvw","getting-started_provider-and-model.md":"1ThPcS9S","getting-started_schedule.md":"DWZZLK7N","getting-started_search-provider.md":"drvsapkH","getting-started_sessions.md":"DG1KsROP","getting-started_skills.md":"C2BuMnIO","getting-started_slash-commands.md":"YJzUIYDB","getting-started_supermarket.md":"CHxQhua4","index.md":"BgCIUzN1","installation_docker.md":"B5sSE5AD","installation_kubernetes.md":"BM4285ww","installation_sqlite.md":"NVW2NTCJ","installation_workspace-backends.md":"DfgrB3f5","memory-providers_builtin.md":"S2mQ6K_Z","memory-providers_index.md":"DGzq3eRm","memory-providers_mem0.md":"SkvoUjPO","memory-providers_openviking.md":"BoPoeSM2","tts-providers_edge.md":"gbwsw0O5","tts-providers_index.md":"CCbWNRJI","zh_about.md":"cMyja04L","zh_channels_dingtalk.md":"qQVPB_wl","zh_channels_discord.md":"BQlW2P9Z","zh_channels_feishu.md":"CHUYOTMb","zh_channels_index.md":"CxXu2vOH","zh_channels_matrix.md":"DoDRytiv","zh_channels_misskey.md":"DMQnfMQl","zh_channels_qq.md":"Bc1PIQqV","zh_channels_slack.md":"CSOD4ML9","zh_channels_telegram.md":"DADq_OAP","zh_channels_wechatoa.md":"BURHbIhD","zh_channels_wecom.md":"So4_Yr06","zh_channels_weixin.md":"BpMbUw3j","zh_getting-started_access.md":"Cc9Ooz-A","zh_getting-started_bot.md":"BOtQUMEA","zh_getting-started_channels.md":"D96VTeND","zh_getting-started_compaction.md":"OuqS_z5q","zh_getting-started_container.md":"DHmJUhnh","zh_getting-started_email.md":"8eVFxsWe","zh_getting-started_files.md":"quzyYFRu","zh_getting-started_heartbeat.md":"Dc0NCjbF","zh_getting-started_mcp.md":"AZutrZeb","zh_getting-started_memory.md":"Chj_g7xR","zh_getting-started_provider-and-model.md":"9Y2SBHJL","zh_getting-started_schedule.md":"D4SFNkZ1","zh_getting-started_search-provider.md":"E0bbpIv6","zh_getting-started_sessions.md":"ByTYMSgA","zh_getting-started_skills.md":"Dkzgim0U","zh_getting-started_slash-commands.md":"ovZ2zmLO","zh_getting-started_supermarket.md":"BcI2nwOn","zh_index.md":"JjoBXiFu","zh_installation_docker.md":"CgAYsIrE","zh_installation_kubernetes.md":"jNBhGJ7z","zh_installation_sqlite.md":"D-j238wQ","zh_installation_workspace-backends.md":"DRIjcct-","zh_memory-providers_builtin.md":"Df2MVDgH","zh_memory-providers_index.md":"DFLiNHIX","zh_memory-providers_mem0.md":"CZLVrH_S","zh_memory-providers_openviking.md":"CDShnWob","zh_tts-providers_edge.md":"BrF316Y6","zh_tts-providers_index.md":"yb-qRJjd"}
